drup/
drup-1.2.1.dist-info/
drup/wrappers.py
drup/librupchecker.cpython-310-x86_64-linux-gnu.so
drup/libdrupchecker.so
drup/__init__.py
drup/cli.py
drup-1.2.1.dist-info/LICENSE
drup-1.2.1.dist-info/WHEEL
drup-1.2.1.dist-info/entry_points.txt
drup-1.2.1.dist-info/top_level.txt
drup-1.2.1.dist-info/METADATA
drup-1.2.1.dist-info/RECORD
