Metadata-Version: 2.1
Name: drup
Version: 1.2.1
Summary: Checks DRUP proofs against DIMACS source. Extracted from verified Why3 code.
Author-email: Matt Fredrikson <mfredrik@cmu.edu>
Project-URL: Homepage, https://github.com/cmu-transparency/verified_rup
Project-URL: Documentation, https://fairlyaccountable.org/verified_rup/drup.html
Project-URL: Bug Tracker, https://github.com/cmu-transparency/verified_rup/issues
Classifier: Programming Language :: Python :: 3
Classifier: Programming Language :: OCaml
Classifier: License :: OSI Approved :: MIT License
Classifier: Operating System :: POSIX :: Linux
Classifier: Operating System :: MacOS :: MacOS X
Classifier: Topic :: Scientific/Engineering :: Mathematics
Requires-Python: >=3.8
License-File: LICENSE
